{
  "updatedAt": "2026-03-14T18:25:57.927702+08:00",
  "timezone": "Asia/Taipei",
  "source": "https://news.cnyes.com/news/cat/tw_stock_news",
  "ok": true,
  "summary": "今日台股新聞重點：1. 1.「這不是2022年！」策略師解析這次能源衝擊為何不同；2. 2.伊朗威脅打擊美國關聯能源設施！美軍空襲哈爾克島後局勢再升級；3. 3.伊朗戰爭進入第三周 美國又從東亞調撥海軍陸戰隊；4. 4.海峽流量暴跌97% 華爾街示警：數十年最嚴重！全球恐陷長期能源危機；5. 5.美以伊開戰第15天戰況彙整：德黑蘭爆炸、伊朗第46波攻勢、川普預告下週「強力空襲」。建議優先關注權值股、ETF 資金流向與政策面消息。",
  "headlines": [
    {
      "title": "1.「這不是2022年！」策略師解析這次能源衝擊為何不同",
      "url": "https://www.cnyes.com/news/id/6384580"
    },
    {
      "title": "2.伊朗威脅打擊美國關聯能源設施！美軍空襲哈爾克島後局勢再升級",
      "url": "https://www.cnyes.com/news/id/6384788"
    },
    {
      "title": "3.伊朗戰爭進入第三周 美國又從東亞調撥海軍陸戰隊",
      "url": "https://www.cnyes.com/news/id/6384712"
    },
    {
      "title": "4.海峽流量暴跌97% 華爾街示警：數十年最嚴重！全球恐陷長期能源危機",
      "url": "https://www.cnyes.com/news/id/6384692"
    },
    {
      "title": "5.美以伊開戰第15天戰況彙整：德黑蘭爆炸、伊朗第46波攻勢、川普預告下週「強力空襲」",
      "url": "https://www.cnyes.com/news/id/6384744"
    }
  ],
  "error": null
}